zinari_sdk/__init__.py
zinari_sdk/sdk.py
zinaripay_sdk-0.2.9.dist-info/LICENSE
zinaripay_sdk-0.2.9.dist-info/METADATA
zinaripay_sdk-0.2.9.dist-info/WHEEL
zinaripay_sdk-0.2.9.dist-info/top_level.txt
zinaripay_sdk-0.2.9.dist-info/RECORD
