Metadata-Version: 2.1
Name: zinaripay-sdk
Version: 0.2.9
Summary: Python SDK for ZinariPay OpenAPI
Home-page: https://github.com/Ramseyxlil/zinari-sdk
Author: Abdulrafiu Izuafa
Author-email: abdulrafiu@techoptimum.org
Classifier: Programming Language :: Python :: 3.8
Classifier: License :: OSI Approved :: MIT License
Classifier: Operating System :: OS Independent
Requires-Python: >=3.6
License-File: LICENSE
Requires-Dist: requests
